linearSubproblemSltns/__init__.py
linearSubproblemSltns/rand_py.py
linearSubproblemSltns/sp1_lib.py
linearSubproblemSltns/sp2E_lib.py
linearSubproblemSltns/sp2_lib.py
linearSubproblemSltns/sp3_lib.py
linearSubproblemSltns/sp4_lib.py
linearSubproblemSltns/sp5_lib.py
linearSubproblemSltns/sp6_lib.py
linearsubproblemsltns-1.0.3.dist-info/METADATA
linearsubproblemsltns-1.0.3.dist-info/WHEEL
linearsubproblemsltns-1.0.3.dist-info/licenses/LICENSE
linearsubproblemsltns-1.0.3.dist-info/RECORD
