Metadata-Version: 2.1
Name: linearSubproblemSltns
Version: 1.0.3
Summary: This is a new tool for multi-joint robotic arm calculations developed at RPI.
Project-URL: Homepage, https://github.com/rpiRobotics/linear-subproblem-solutions
Project-URL: Bug Tracker, https://github.com/rpiRobotics/linear-subproblem-solutions/issues
Project-URL: Paper, https://arxiv.org/pdf/2211.05737.pdf
Author-email: Alexander Elias <eliasa3@rpi.edu>, Ashton Ropp <ashr8011@gmail.com>
License-File: LICENSE
Classifier: License :: OSI Approved :: BSD License
Classifier: Operating System :: OS Independent
Classifier: Programming Language :: Python :: 3
Requires-Python: >=3.7
Requires-Dist: numpy>=1.22.3
Requires-Dist: scipy>=1.10.0
